[
    {
        "model": "furxapi.todolist",
        "pk": 1,
        "comments": "this is dummy data for a stretch goal",
        "fields": {
            "user": 1,
            "to_do_action": "separate our finances",
            "completed": false
        }
    },
    {
        "model": "furxapi.todolist",
        "pk": 2,
        "comments": "this is dummy data for a stretch goal",
        "fields": {
            "user": 2,
            "to_do_action": "find new apartment",
            "completed": false
        }
    }
]